{"daily-notes_issue-7.md":"0eea3c2d","daily-notes_issue-8.md":"b2f4d218","daily-notes_issue-6.md":"e6da4132","daily-notes_issue-41.md":"a553cdf7","daily-notes_issue-42.md":"e86cc20f","daily-notes_issue-5.md":"db6279c3","daily-notes_issue-4.md":"a4c0a099","efficiency_software_windows.md":"60ff91af","daily-notes_issue-9.md":"7369d4fb","efficiency_bookmark-scripts.md":"f676c384","efficiency_online-tools.md":"8e44416f","efficiency_software_vscode.md":"9c427756","efficiency_software_webstorm.md":"d6979821","fe_browser_index.md":"90bfa6a2","fe_coding_index.md":"1003f52e","fe_concept_module.md":"a9afe34c","fe_concept_page-rendering.md":"11cfdc77","analysis_react_18.md":"2e882cd4","analysis_utils_clsx.md":"91f225d8","analysis_utils_only-allow.md":"84d24b61","daily-notes_index.md":"70819b1f","daily-notes_issue-1.md":"0b467682","daily-notes_issue-10.md":"d2f72b26","daily-notes_issue-11.md":"6a20a61f","daily-notes_issue-12.md":"e78a0576","daily-notes_issue-13.md":"29f51cd2","daily-notes_issue-14.md":"ad570548","daily-notes_issue-15.md":"7af029ea","daily-notes_issue-16.md":"0edadcce","daily-notes_issue-17.md":"193f5609","daily-notes_issue-18.md":"e583ff5d","daily-notes_issue-19.md":"0590b3eb","daily-notes_issue-2.md":"2bf88afa","daily-notes_issue-20.md":"188ec941","daily-notes_issue-21.md":"870d00e2","daily-notes_issue-22.md":"e7f957b9","daily-notes_issue-23.md":"67b3e014","daily-notes_issue-25.md":"0efedf30","daily-notes_issue-26.md":"7a34475b","daily-notes_issue-27.md":"e2e7b59a","daily-notes_issue-28.md":"ff3f73d1","daily-notes_issue-29.md":"a761283f","daily-notes_issue-3.md":"2ff8d540","daily-notes_issue-30.md":"9b32be72","fe_css_index.md":"7fca467d","fe_javascript_clone.md":"28432ee1","fe_javascript_conversions.md":"f7c3e378","fe_javascript_inherit.md":"86035cbd","fe_javascript_prototype.md":"0b37a13e","fe_javascript_types.md":"3e987305","fe_network_http.md":"cc36dc0d","fe_network_tcp.md":"cfc0339a","fe_node_pkg.md":"a2ed1a6b","daily-notes_issue-31.md":"49b0191f","daily-notes_issue-33.md":"b431ce29","daily-notes_issue-34.md":"e3545611","fe_typescript_base.md":"d75b8917","fe_typescript_challenges.md":"34711f71","fe_typescript_tsconfig.md":"da365647","fe_webpack_index.md":"49856759","index.md":"b143fd52","mao.md":"c9b87ba9","nav.md":"225db29f","pit_h5.md":"0c701a69","pit_library.md":"b05b11de","pit_npm.md":"6795fc26","pit_pc.md":"6852c3ba","daily-notes_issue-35.md":"f54aac22","workflow_css_spec.md":"93be5701","daily-notes_issue-36.md":"0be193b2","workflow_css_tricks.md":"10864af9","workflow_git_command.md":"b4a6db03","daily-notes_issue-37.md":"b7489630","workflow_node_npm.md":"a690b1a1","workflow_sass_index.md":"42d1c3d5","workflow_style-guide.md":"b5740ddb","daily-notes_issue-38.md":"1d9f6be5","workflow_terminal_shell.md":"1c8d7be9","daily-notes_issue-39.md":"99a253e6","workflow_utils_library.md":"86749e99","workflow_utils_regexp.md":"36562b16","workflow_terminal_toolkit.md":"88af1888","efficiency_software_cross-platform.md":"caf2097f","efficiency_software_browser.md":"215a9eaf","workflow_terminal_zsh.md":"bd9bc1ac","workflow_utils_function.md":"ad3f60b8","daily-notes_issue-24.md":"94556d5a","fe_html_index.md":"4f05ae25","efficiency_software_mac.md":"9cacfb8f","workflow_git_index.md":"b6b4ae9d","workflow_library_dayjs.md":"ee3112e6","fe_es6_index.md":"bb878afb","workflow_library_tailwindcss.md":"b37fbdb4","workflow_vue_index.md":"6259d080"}
